binarycookies/__init__.py
binarycookies/__main__.py
binarycookies/_deserialize.py
binarycookies/_output_handlers.py
binarycookies/_serialize.py
binarycookies/models.py
binarycookies/parser.py
binarycookies/py.typed
binarycookies-2.3.0.dist-info/entry_points.txt
binarycookies-2.3.0.dist-info/LICENSE
binarycookies-2.3.0.dist-info/WHEEL
binarycookies-2.3.0.dist-info/METADATA
binarycookies-2.3.0.dist-info/RECORD
